ocp_gordon/__init__.py
ocp_gordon/py.typed
ocp_gordon/internal/__init__.py
ocp_gordon/internal/approx_result.py
ocp_gordon/internal/bspline_algorithms.py
ocp_gordon/internal/bspline_approx_interp.py
ocp_gordon/internal/curve_network_sorter.py
ocp_gordon/internal/curves_to_surface.py
ocp_gordon/internal/error.py
ocp_gordon/internal/gordon_surface_builder.py
ocp_gordon/internal/interpolate_curve_network.py
ocp_gordon/internal/intersect_bsplines.py
ocp_gordon/internal/misc.py
ocp_gordon/internal/points_to_bspline_interpolation.py
ocp_gordon-0.2.0.dist-info/licenses/LICENSE
ocp_gordon-0.2.0.dist-info/METADATA
ocp_gordon-0.2.0.dist-info/WHEEL
ocp_gordon-0.2.0.dist-info/top_level.txt
ocp_gordon-0.2.0.dist-info/RECORD
