Metadata-Version: 2.4
Name: ocp_gordon
Version: 0.2.0
Summary: A Python library for Gordon Surface interpolation using B-splines.
Author-email: Fan Gong <gongfan99@hotmail.com>
License-Expression: Apache-2.0
Project-URL: Homepage, https://github.com/gongfan99/ocp_gordon
Project-URL: Issues, https://github.com/gongfan99/ocp_gordon/issues
Project-URL: Used-by, https://github.com/gumyr/build123d
Keywords: 3d models,3d printing,3d,brep,cad,cadquery,build123d,opencascade,python
Classifier: Programming Language :: Python :: 3
Classifier: Operating System :: OS Independent
Classifier: Topic :: Scientific/Engineering :: Mathematics
Classifier: Topic :: Software Development :: Libraries :: Python Modules
Requires-Python: <3.15,>=3.10
License-File: LICENSE
Requires-Dist: cadquery_ocp_proxy<8.0,>=7.9
Requires-Dist: numpy<3,>=2
Requires-Dist: scipy
Provides-Extra: test
Requires-Dist: pytest; extra == "test"
Requires-Dist: cadquery_ocp_novtk<8.0,>=7.9; extra == "test"
Provides-Extra: stubs
Requires-Dist: cadquery-ocp-stubs<8.0,>=7.9; extra == "stubs"
Dynamic: license-file
